{
  "pools": [
    {
      "rolls": 1,
      "entries": [
        {
          "type": "minecraft:item",
          "name": "minecraft:diamond_pickaxe",
          "functions": [
            {
              "function": "minecraft:set_custom_data",
              "tag": {
                "starwars": {
                  "right_click": true,
                  "flamethrower": true
                }
              }
            },
            {
              "function": "minecraft:set_components",
              "components": {
                "minecraft:item_name": {"translate": "item.starwars.blaster.bt_x-42"},
                "minecraft:consumable": {
                  "consume_seconds": 1e+38,
                  "animation": "bow",
                  "has_consume_particles": false
                },
                "item_model": "starwars:blaster/bt_x-42",
                "!minecraft:tool": {}
              }
            }
          ]
        }
      ]
    }
  ]
}